embedding/__init__.py
embedding/embedding.py
embeddings_util/__init__.py
embeddings_util/embeddings_util.py
embeddings_util-1.0.1.dist-info/LICENSE.txt
embeddings_util-1.0.1.dist-info/METADATA
embeddings_util-1.0.1.dist-info/WHEEL
embeddings_util-1.0.1.dist-info/top_level.txt
embeddings_util-1.0.1.dist-info/RECORD
