Metadata-Version: 2.1
Name: embeddings-util
Version: 1.0.1
Summary: The embeddings package is a utility for generating question-answer pairs and embeddings from HTML pages or text input. It utilizes the OpenAI API to generate question-answer pairs and embeddings. This package is useful for generating training data for chatbots or question-answering models.
Home-page: https://github.com/ChatClue/embedding-python
Author: Osiris Development LLC
Author-email: support@pagepixels.com
License: UNKNOWN
Platform: UNKNOWN
Classifier: Development Status :: 4 - Beta
Classifier: Intended Audience :: Developers
Classifier: License :: OSI Approved :: MIT License
Classifier: Operating System :: OS Independent
Classifier: Programming Language :: Python
Classifier: Programming Language :: Python :: 3
Classifier: Programming Language :: Python :: 3.6
Classifier: Programming Language :: Python :: 3.7
Classifier: Programming Language :: Python :: 3.8
Classifier: Programming Language :: Python :: 3.9
License-File: LICENSE.txt
Requires-Dist: requests
Requires-Dist: screenshots-pagepixels
Requires-Dist: bs4
